source_gcs/__init__.py
source_gcs/config.py
source_gcs/config_migrations.py
source_gcs/cursor.py
source_gcs/helpers.py
source_gcs/legacy_config_transformer.py
source_gcs/run.py
source_gcs/source.py
source_gcs/spec.py
source_gcs/stream.py
source_gcs/stream_reader.py
source_gcs/zip_helper.py
airbyte_source_gcs-0.10.4.dist-info/METADATA
airbyte_source_gcs-0.10.4.dist-info/WHEEL
airbyte_source_gcs-0.10.4.dist-info/entry_points.txt
airbyte_source_gcs-0.10.4.dist-info/RECORD
